qlcpy/__init__.py
qlcpy/__main__.py
qlcpy/arrays.py
qlcpy/generator.py
qlcpy/models.py
qlcpy/primitives.py
qlcpy/i18n/__init__.py
qlcpy/i18n/en.py
qlcpy/i18n/fi.py
qlcpy/instrument/Instrumentor.py
qlcpy/instrument/ProgramData.py
qlcpy/instrument/TransformAST.py
qlcpy/instrument/TransformForInstrumentor.py
qlcpy/instrument/VariableRole.py
qlcpy/instrument/WalkAST.py
qlcpy/instrument/WalkErrorCauses.py
qlcpy/instrument/WalkFind.py
qlcpy/instrument/WalkLinePurposes.py
qlcpy/instrument/WalkNames.py
qlcpy/instrument/WalkNext.py
qlcpy/instrument/__init__.py
qlcpy/instrument/trees.py
qlcpy/questions/__init__.py
qlcpy/questions/dynamic.py
qlcpy/questions/lines.py
qlcpy/questions/names.py
qlcpy/questions/options.py
qlcpy/questions/purpose.py
qlcpy-1.0.18.dist-info/LICENSE
qlcpy-1.0.18.dist-info/METADATA
qlcpy-1.0.18.dist-info/WHEEL
qlcpy-1.0.18.dist-info/entry_points.txt
qlcpy-1.0.18.dist-info/top_level.txt
qlcpy-1.0.18.dist-info/RECORD
