Metadata-Version: 2.1
Name: qlcpy
Version: 1.0.18
Summary: Generates questions about given Python program
Home-page: https://github.com/teemulehtinen/qlcpy
Author: Teemu Lehtinen
Author-email: teemu.t.lehtinen@aalto.fi
Classifier: Programming Language :: Python :: 3
Classifier: License :: OSI Approved :: MIT License
Classifier: Operating System :: OS Independent
Requires-Python: >=3.6
License-File: LICENSE
